pydantic_wrangler/__init__.py
pydantic_wrangler/config.py
pydantic_wrangler/custom_collections.py
pydantic_wrangler/datastore.py
pydantic_wrangler/dumpers.py
pydantic_wrangler/exceptions.py
pydantic_wrangler/loaders.py
pydantic_wrangler/models.py
pydantic_wrangler/utils.py
pydantic_wrangler-0.1.0.dist-info/LICENSE
pydantic_wrangler-0.1.0.dist-info/METADATA
pydantic_wrangler-0.1.0.dist-info/WHEEL
pydantic_wrangler-0.1.0.dist-info/RECORD
