Metadata-Version: 2.1
Name: pydantic_wrangler
Version: 0.1.0
Summary: A Python package that standardizes data parsing from multiple serilized formats into pydantic models.
License: MIT
Keywords: serialization,deserialization,parsing,pydantic-models,seria-to-pydantic,pydantic-to-serial
Author: André Lima
Requires-Python: >=3.9,<4.0
Classifier: License :: OSI Approved :: MIT License
Classifier: Programming Language :: Python :: 3
Classifier: Programming Language :: Python :: 3.9
Classifier: Programming Language :: Python :: 3.10
Classifier: Programming Language :: Python :: 3.11
Classifier: Programming Language :: Python :: 3.12
Requires-Dist: jinja2 (>=3.1.3,<4.0.0)
Requires-Dist: pydantic (>=2.6.1,<3.0.0)
Requires-Dist: pyyaml (>=6.0.1,<7.0.0)
Requires-Dist: sortedcontainers (>=2.4.0,<3.0.0)
Requires-Dist: toml (>=0.10.2,<0.11.0)
Project-URL: Documentation, https://github.com/theandrelima/pydantic-wrangler
